foxypack_x_twikit-0.0.4.dist-info/METADATA
foxypack_x_twikit-0.0.4.dist-info/WHEEL
foxypack_x_twikit-0.0.4.dist-info/entry_points.txt
foxypack_x_twikit/__init__.py
foxypack_x_twikit/engine.py
foxypack_x_twikit-0.0.4.dist-info/RECORD
