Metadata-Version: 2.1
Name: foxypack-x-twikit
Version: 0.0.4
Summary: Default template for PDM package
Author-Email: shapdi <shapranov.work@gmail.com>
License: MIT
Requires-Python: >=3.10
Requires-Dist: foxypack>=0.0.5
Requires-Dist: twikitminifix==2.3.7
Provides-Extra: dev
Requires-Dist: ruff>=0.14.0; extra == "dev"
